albumentations_mcp/__init__.py
albumentations_mcp/__main__.py
albumentations_mcp/config.py
albumentations_mcp/errors.py
albumentations_mcp/image_conversions.py
albumentations_mcp/parser.py
albumentations_mcp/pipeline.py
albumentations_mcp/presets.py
albumentations_mcp/processor.py
albumentations_mcp/recovery.py
albumentations_mcp/server.py
albumentations_mcp/validation.py
albumentations_mcp/verification.py
albumentations_mcp/hooks/__init__.py
albumentations_mcp/hooks/post_mcp.py
albumentations_mcp/hooks/post_save.py
albumentations_mcp/hooks/post_transform.py
albumentations_mcp/hooks/post_transform_verify.py
albumentations_mcp/hooks/pre_mcp.py
albumentations_mcp/hooks/pre_save.py
albumentations_mcp/hooks/pre_transform.py
albumentations_mcp/hooks/utils.py
albumentations_mcp/utils/__init__.py
albumentations_mcp/utils/async_utils.py
albumentations_mcp/utils/error_utils.py
albumentations_mcp/utils/file_utils.py
albumentations_mcp/utils/image_handler.py
albumentations_mcp/utils/logging_utils.py
albumentations_mcp/utils/memory_utils.py
albumentations_mcp/utils/seed_utils.py
albumentations_mcp/utils/singleton_utils.py
albumentations_mcp/utils/validation_utils.py
albumentations_mcp/vlm/__init__.py
albumentations_mcp/vlm/base.py
albumentations_mcp/vlm/config.py
albumentations_mcp/vlm/google_gemini.py
albumentations_mcp/py.typed
albumentations_mcp-1.0.2.dist-info/METADATA
albumentations_mcp-1.0.2.dist-info/WHEEL
albumentations_mcp-1.0.2.dist-info/entry_points.txt
albumentations_mcp-1.0.2.dist-info/licenses/LICENSE
albumentations_mcp-1.0.2.dist-info/RECORD
