Metadata-Version: 2.4
Name: albumentations-mcp
Version: 1.0.2
Summary: MCP-compliant image augmentation server using Albumentations
Project-URL: Homepage, https://github.com/ramsi-k/albumentations-mcp
Project-URL: Repository, https://github.com/ramsi-k/albumentations-mcp
Project-URL: Issues, https://github.com/ramsi-k/albumentations-mcp/issues
Author-email: Ramsi Kalia <ramsi.kalia@gmail.com>
License: MIT License
License-File: LICENSE
Keywords: ai,albumentations,computer-vision,data-augmentation,gemini,google-genai,image-augmentation,image-editing,image-generation,mcp,mcp-server,semantic-augmentation,vlm
Classifier: Development Status :: 5 - Production/Stable
Classifier: Intended Audience :: Developers
Classifier: License :: OSI Approved :: MIT License
Classifier: Operating System :: OS Independent
Classifier: Programming Language :: Python
Classifier: Programming Language :: Python :: 3
Classifier: Programming Language :: Python :: 3 :: Only
Classifier: Programming Language :: Python :: 3.12
Classifier: Topic :: Scientific/Engineering :: Artificial Intelligence
Classifier: Topic :: Software Development :: Libraries :: Python Modules
Classifier: Typing :: Typed
Requires-Python: >=3.12
Requires-Dist: albumentations>=1.3.0
Requires-Dist: httpx<0.28
Requires-Dist: mcp[cli]<2,>=1.12
Requires-Dist: numpy>=1.26.0
Requires-Dist: opencv-python-headless>=4.8.0
Requires-Dist: pillow>=10.0.0
Requires-Dist: pre-commit>=4.2.0
Requires-Dist: pydantic>=2.0.0
Provides-Extra: dev
Requires-Dist: black>=23.0.0; extra == 'dev'
Requires-Dist: pre-commit>=3.0.0; extra == 'dev'
Requires-Dist: pytest-asyncio>=0.21.0; extra == 'dev'
Requires-Dist: pytest>=7.0.0; extra == 'dev'
Requires-Dist: ruff>=0.1.0; extra == 'dev'
Provides-Extra: vlm
Requires-Dist: google-genai>=0.2.0; extra == 'vlm'
